hatch_global_env_vars/__about__.py
hatch_global_env_vars/__init__.py
hatch_global_env_vars/hooks.py
hatch_global_env_vars/plugin.py
hatch_global_env_vars/py.typed
hatch_global_env_vars-1.0.0.dist-info/METADATA
hatch_global_env_vars-1.0.0.dist-info/WHEEL
hatch_global_env_vars-1.0.0.dist-info/entry_points.txt
hatch_global_env_vars-1.0.0.dist-info/licenses/LICENSE.txt
hatch_global_env_vars-1.0.0.dist-info/RECORD
