Metadata-Version: 2.4
Name: hatch-global-env-vars
Version: 1.0.0
Summary: Hatch environment collector plugin that sets global dynamic environment variables
Project-URL: History, https://github.com/valentinoli/hatch-global-env-vars/blob/main/HISTORY.md
Project-URL: Issues, https://github.com/valentinoli/hatch-global-env-vars/issues
Project-URL: Source, https://github.com/valentinoli/hatch-global-env-vars
Author-email: Valentin Oliver Melberg Loftsson <valentin.loftsson@gmail.com>
License-File: LICENSE.txt
Keywords: hatch,plugin
Classifier: Development Status :: 4 - Beta
Classifier: Framework :: Hatch
Classifier: Operating System :: OS Independent
Classifier: Programming Language :: Python
Classifier: Programming Language :: Python :: 3.11
Classifier: Programming Language :: Python :: 3.12
Classifier: Programming Language :: Python :: 3.13
Classifier: Programming Language :: Python :: 3.14
Classifier: Programming Language :: Python :: Implementation :: CPython
Classifier: Programming Language :: Python :: Implementation :: PyPy
Requires-Python: >=3.11
Requires-Dist: hatch
